statemachine_engine/__init__.py
statemachine_engine/cli.py
statemachine_engine/actions/__init__.py
statemachine_engine/actions/base.py
statemachine_engine/actions/builtin/__init__.py
statemachine_engine/actions/builtin/bash_action.py
statemachine_engine/actions/builtin/check_database_queue_action.py
statemachine_engine/actions/builtin/check_machine_state_action.py
statemachine_engine/actions/builtin/clear_events_action.py
statemachine_engine/actions/builtin/log_action.py
statemachine_engine/actions/builtin/send_event_action.py
statemachine_engine/core/__init__.py
statemachine_engine/core/action_loader.py
statemachine_engine/core/engine.py
statemachine_engine/core/health_monitor.py
statemachine_engine/database/__init__.py
statemachine_engine/database/cli.py
statemachine_engine/database/models/__init__.py
statemachine_engine/database/models/base.py
statemachine_engine/database/models/job.py
statemachine_engine/database/models/machine_event.py
statemachine_engine/database/models/machine_state.py
statemachine_engine/database/models/realtime_event.py
statemachine_engine/database/schema/generic/001_jobs.sql
statemachine_engine/database/schema/generic/002_machine_events.sql
statemachine_engine/database/schema/generic/003_machine_state.sql
statemachine_engine/database/schema/generic/004_realtime_events.sql
statemachine_engine/monitoring/__init__.py
statemachine_engine/monitoring/async_logging.py
statemachine_engine/monitoring/websocket_server.py
statemachine_engine/tools/__init__.py
statemachine_engine/tools/cli.py
statemachine_engine/tools/config.py
statemachine_engine/tools/diagrams.py
statemachine_engine/tools/event_monitor.py
statemachine_engine/tools/validate.py
statemachine_engine/ui/cli.py
statemachine_engine/ui/package-lock.json
statemachine_engine/ui/package.json
statemachine_engine/ui/server.js
statemachine_engine/ui/node_modules/.package-lock.json
statemachine_engine/ui/node_modules/@gar/promisify/index.js
statemachine_engine-1.0.31.dist-info/licenses/LICENSE
statemachine_engine-1.0.31.dist-info/METADATA
statemachine_engine-1.0.31.dist-info/WHEEL
statemachine_engine-1.0.31.dist-info/entry_points.txt
statemachine_engine-1.0.31.dist-info/top_level.txt
statemachine_engine-1.0.31.dist-info/RECORD
