Metadata-Version: 2.4
Name: statemachine-engine
Version: 1.0.31
Summary: A generic, event-driven state machine framework with real-time monitoring
Author-email: Sami Heikkinen <sheikki@yahoo.com>
License: MIT
Project-URL: Homepage, https://github.com/sheikkinen/statemachine-engine
Project-URL: Documentation, https://github.com/sheikkinen/statemachine-engine#readme
Project-URL: Repository, https://github.com/sheikkinen/statemachine-engine
Project-URL: Issues, https://github.com/sheikkinen/statemachine-engine/issues
Project-URL: Changelog, https://github.com/sheikkinen/statemachine-engine/blob/main/CHANGELOG.md
Keywords: state-machine,workflow,event-driven,fsm,automation,orchestration
Classifier: Development Status :: 4 - Beta
Classifier: Intended Audience :: Developers
Classifier: License :: OSI Approved :: MIT License
Classifier: Programming Language :: Python :: 3
Classifier: Programming Language :: Python :: 3.9
Classifier: Programming Language :: Python :: 3.10
Classifier: Programming Language :: Python :: 3.11
Classifier: Programming Language :: Python :: 3.12
Classifier: Topic :: Software Development :: Libraries :: Python Modules
Classifier: Topic :: System :: Distributed Computing
Requires-Python: >=3.9
License-File: LICENSE
Requires-Dist: PyYAML>=6.0
Requires-Dist: fastapi>=0.104.0
Requires-Dist: uvicorn>=0.24.0
Requires-Dist: websockets>=12.0
Requires-Dist: tabulate>=0.9.0
Provides-Extra: dev
Requires-Dist: pytest>=7.0; extra == "dev"
Requires-Dist: pytest-asyncio>=0.21; extra == "dev"
Requires-Dist: httpx>=0.25.0; extra == "dev"
Dynamic: license-file
